invsearch/__init__.py
invsearch/__init__.pyc
invsearch/inv_index.py
invsearch/inv_index.pyc
invsearch/__pycache__/__init__.cpython-34.pyc
invsearch/__pycache__/__init__.cpython-35.pyc
invsearch/__pycache__/__init__.cpython-36.pyc
invsearch/__pycache__/inv_index.cpython-34.pyc
invsearch/__pycache__/inv_index.cpython-35.pyc
invsearch/__pycache__/inv_index.cpython-36.pyc
invsearch-0.0.2.dist-info/AUTHORS.rst
invsearch-0.0.2.dist-info/LICENSE.txt
invsearch-0.0.2.dist-info/METADATA
invsearch-0.0.2.dist-info/WHEEL
invsearch-0.0.2.dist-info/top_level.txt
invsearch-0.0.2.dist-info/RECORD
