Metadata-Version: 2.1
Name: invsearch
Version: 0.0.2
Summary: Search Document by Field and Value.
Home-page: https://github.com/MacHu-GWU/
Author: Sanhe Hu
Author-email: husanhe@gmail.com
Maintainer: Sanhe Hu
Maintainer-email: husanhe@gmail.com
License: MIT
Download-URL: https://pypi.python.org/pypi/invsearch/0.0.2#downloads
Platform: Windows
Platform: MacOS
Platform: Unix
Classifier: Development Status :: 4 - Beta
Classifier: Intended Audience :: Developers
Classifier: License :: OSI Approved :: MIT License
Classifier: Natural Language :: English
Classifier: Operating System :: Microsoft :: Windows
Classifier: Operating System :: MacOS
Classifier: Operating System :: Unix
Classifier: Programming Language :: Python
Classifier: Programming Language :: Python :: 2.7
Classifier: Programming Language :: Python :: 3.4
Classifier: Programming Language :: Python :: 3.5
Classifier: Programming Language :: Python :: 3.6
Requires-Dist: six
Requires-Dist: sentinels
Provides-Extra: docs
Requires-Dist: sphinx (==1.8.1); extra == 'docs'
Requires-Dist: sphinx-rtd-theme; extra == 'docs'
Requires-Dist: sphinx-jinja; extra == 'docs'
Requires-Dist: sphinx-copybutton; extra == 'docs'
Requires-Dist: docfly (>=0.0.16); extra == 'docs'
Requires-Dist: rstobj; extra == 'docs'
Requires-Dist: pygments; extra == 'docs'
Provides-Extra: tests
Requires-Dist: pytest (>=3.2.3); extra == 'tests'
Requires-Dist: pytest-cov; extra == 'tests'
